waafle/__init__.py
waafle/utils.py
waafle/waafle_genecaller.py
waafle/waafle_junctions.py
waafle/waafle_orgscorer.py
waafle/waafle_qc.py
waafle/waafle_search.py
waafle-1.0.0.dist-info/LICENSE.txt
waafle-1.0.0.dist-info/METADATA
waafle-1.0.0.dist-info/WHEEL
waafle-1.0.0.dist-info/entry_points.txt
waafle-1.0.0.dist-info/top_level.txt
waafle-1.0.0.dist-info/RECORD
