Metadata-Version: 2.1
Name: waafle
Version: 1.0.0
Summary: WAAFLE: a Workflow to Annotate Assemblies and Find LGT Events
Home-page: https://huttenhower.sph.harvard.edu/waafle
Author: Eric Franzosa
Author-email: franzosa@hsph.harvard.edu
License: MIT
Platform: UNKNOWN
Classifier: Programming Language :: Python
Requires-Dist: numpy >=1.13.0
